{
  "last_scan": "2026-03-19T19:58:53.426469+00:00",
  "total": 134,
  "available_count": 60,
  "results": {
    "888 Bellevue": {
      "name": "888 Bellevue",
      "city": "Bellevue",
      "url": "https://www.888bellevue.com/",
      "status": "error",
      "signal": "none",
      "details": "",
      "checked_at": "2026-03-19T19:54:16.812291+00:00",
      "error": "403 Client Error: Forbidden for url: https://www.888bellevue.com/",
      "has_3br": false,
      "has_den": false,
      "in_budget": true
    },
    "AMLI Arc": {
      "name": "AMLI Arc",
      "city": "Bellevue",
      "url": "https://www.amli.com/apartments/seattle/bellevue-apartments/amli-bellevue-park/floorplans",
      "status": "available",
      "signal": "strong",
      "details": "Keywords: available now, schedule a tour [3BR, den/loft]",
      "checked_at": "2026-03-19T19:54:18.542153+00:00",
      "error": null,
      "has_3br": true,
      "has_den": true,
      "in_budget": true,
      "min_rent_found": 2228
    },
    "AMLI Spring District": {
      "name": "AMLI Spring District",
      "city": "Bellevue",
      "url": "https://www.amli.com/apartments/seattle/bellevue-apartments/amli-spring-district",
      "status": "available",
      "signal": "strong",
      "details": "Keywords: schedule a tour, available units [3BR, den/loft]",
      "checked_at": "2026-03-19T19:54:20.307978+00:00",
      "error": null,
      "has_3br": true,
      "has_den": true,
      "in_budget": true,
      "min_rent_found": 2229
    },
    "Alley 111": {
      "name": "Alley 111",
      "city": "Bellevue",
      "url": "https://www.alley111.com",
      "status": "available",
      "signal": "strong",
      "details": "Keywords: apply now, schedule a tour [den/loft]",
      "checked_at": "2026-03-19T19:54:21.943871+00:00",
      "error": null,
      "has_3br": false,
      "has_den": true,
      "in_budget": true
    },
    "Ascent Bellevue": {
      "name": "Ascent Bellevue",
      "city": "Bellevue",
      "url": "https://www.essexapartmenthomes.com/apartments/kirkland/ascent/floor-plans-and-pricing",
      "status": "available",
      "signal": "strong",
      "details": "Keywords: apply now, schedule a tour [3BR, den/loft]",
      "checked_at": "2026-03-19T19:54:23.715442+00:00",
      "error": null,
      "has_3br": true,
      "has_den": true,
      "in_budget": true
    },
    "Avalon Meydenbauer": {
      "name": "Avalon Meydenbauer",
      "city": "Bellevue",
      "url": "https://www.avaloncommunities.com/washington/bellevue-apartments/avalon-meydenbauer/",
      "status": "available",
      "signal": "strong",
      "details": "Keywords: \\d+ available, available.*\\d+ bed [den/loft]",
      "checked_at": "2026-03-19T19:54:26.577253+00:00",
      "error": null,
      "has_3br": false,
      "has_den": true,
      "in_budget": true
    },
    "Bellevue 10": {
      "name": "Bellevue 10",
      "city": "Bellevue",
      "url": "https://bellevue10.com/",
      "status": "available",
      "signal": "strong",
      "details": "Keywords: apply now, schedule a tour [3BR, den/loft]",
      "checked_at": "2026-03-19T19:54:29.491990+00:00",
      "error": null,
      "has_3br": true,
      "has_den": true,
      "in_budget": true
    },
    "Bellevue Heights": {
      "name": "Bellevue Heights",
      "city": "Bellevue",
      "url": "https://www.bellevue-heights.com/",
      "status": "available",
      "signal": "strong",
      "details": "Keywords: available.*\\d+ bed",
      "checked_at": "2026-03-19T19:54:31.295063+00:00",
      "error": null,
      "has_3br": false,
      "has_den": false,
      "in_budget": true
    },
    "Bellevue Meadows": {
      "name": "Bellevue Meadows",
      "city": "Bellevue",
      "url": "https://www.equityapartments.com/seattle/redmond/bellevue-meadows-apartments",
      "status": "error",
      "signal": "none",
      "details": "",
      "checked_at": "2026-03-19T19:54:33.159775+00:00",
      "error": "403 Client Error: Forbidden for url: https://www.equityapartments.com/seattle/redmond/bellevue-meado",
      "has_3br": false,
      "has_den": false,
      "in_budget": true
    },
    "Bellevue Ridge": {
      "name": "Bellevue Ridge",
      "city": "Bellevue",
      "url": "https://www.bellevueridgeapts.com",
      "status": "unknown",
      "signal": "none",
      "details": "No clear availability signal | den/loft detected",
      "checked_at": "2026-03-19T19:54:34.827673+00:00",
      "error": null,
      "has_3br": false,
      "has_den": true,
      "in_budget": true,
      "min_rent_found": 1495
    },
    "Borgata": {
      "name": "Borgata",
      "city": "Bellevue",
      "url": "https://www.borgatabellevue.com",
      "status": "available",
      "signal": "strong",
      "details": "Keywords: schedule a tour [den/loft]",
      "checked_at": "2026-03-19T19:54:36.607709+00:00",
      "error": null,
      "has_3br": false,
      "has_den": true,
      "in_budget": true,
      "min_rent_found": 900
    },
    "Bridle Trails Apartments": {
      "name": "Bridle Trails Apartments",
      "city": "Bellevue",
      "url": "https://www.bridletrailsapts.com",
      "status": "available",
      "signal": "strong",
      "details": "Keywords: apply now, schedule a tour [3BR, den/loft]",
      "checked_at": "2026-03-19T19:54:38.305608+00:00",
      "error": null,
      "has_3br": true,
      "has_den": true,
      "in_budget": true,
      "min_rent_found": 1809
    },
    "Brio": {
      "name": "Brio",
      "city": "Bellevue",
      "url": "https://www.udr.com/seattle-apartments/bellevue/brio/",
      "status": "unknown",
      "signal": "none",
      "details": "No clear availability signal | den/loft detected",
      "checked_at": "2026-03-19T19:54:42.554397+00:00",
      "error": null,
      "has_3br": false,
      "has_den": true,
      "in_budget": true,
      "min_rent_found": 1897
    },
    "Camden Bellevue": {
      "name": "Camden Bellevue",
      "city": "Bellevue",
      "url": "https://www.camdenliving.com/apartments/bellevue-wa/camden-bellevue",
      "status": "unknown",
      "signal": "none",
      "details": "No clear availability signal | 3BR detected, den/loft detected",
      "checked_at": "2026-03-19T19:54:44.810274+00:00",
      "error": null,
      "has_3br": true,
      "has_den": true,
      "in_budget": true,
      "min_rent_found": 1169
    },
    "Carrington Apartments": {
      "name": "Carrington Apartments",
      "city": "Bellevue",
      "url": "https://www.carringtonplaceredmond.com",
      "status": "error",
      "signal": "none",
      "details": "",
      "checked_at": "2026-03-19T19:54:46.872159+00:00",
      "error": "connection_error",
      "has_3br": false,
      "has_den": false,
      "in_budget": true
    },
    "Catalina Community": {
      "name": "Catalina Community",
      "city": "Bellevue",
      "url": "https://www.catalinabellevue.com",
      "status": "error",
      "signal": "none",
      "details": "",
      "checked_at": "2026-03-19T19:54:48.420081+00:00",
      "error": "403 Client Error: Forbidden for url: https://www.catalinabellevue.com/",
      "has_3br": false,
      "has_den": false,
      "in_budget": true
    },
    "Cerasa": {
      "name": "Cerasa",
      "city": "Bellevue",
      "url": "https://www.cerasabellevue.com",
      "status": "available",
      "signal": "strong",
      "details": "Keywords: apply now [den/loft]",
      "checked_at": "2026-03-19T19:54:50.226747+00:00",
      "error": null,
      "has_3br": false,
      "has_den": true,
      "in_budget": true
    },
    "CityScape": {
      "name": "CityScape",
      "city": "Bellevue",
      "url": "https://www.cityscapebellevue.com",
      "status": "available",
      "signal": "strong",
      "details": "Keywords: schedule a tour, available units [den/loft]",
      "checked_at": "2026-03-19T19:54:52.983046+00:00",
      "error": null,
      "has_3br": false,
      "has_den": true,
      "in_budget": true,
      "min_rent_found": 2095
    },
    "Colonial Square": {
      "name": "Colonial Square",
      "city": "Bellevue",
      "url": "https://washington.weidner.com/apartments/wa/bellevue/colonial-square-3/",
      "status": "error",
      "signal": "none",
      "details": "",
      "checked_at": "2026-03-19T19:54:54.766942+00:00",
      "error": "403 Client Error: Forbidden for url: https://washington.weidner.com/apartments/wa/bellevue/colonial-",
      "has_3br": false,
      "has_den": false,
      "in_budget": true
    },
    "Ellington at Bellevue": {
      "name": "Ellington at Bellevue",
      "city": "Bellevue",
      "url": "https://www.essexapartmenthomes.com/apartments/bellevue/ellington-at-bellevue",
      "status": "available",
      "signal": "strong",
      "details": "Keywords: apply now, schedule a tour [3BR, den/loft]",
      "checked_at": "2026-03-19T19:54:56.408080+00:00",
      "error": null,
      "has_3br": true,
      "has_den": true,
      "in_budget": true,
      "min_rent_found": 1837
    },
    "Esterra Apartments Phase II": {
      "name": "Esterra Apartments Phase II",
      "city": "Bellevue",
      "url": "https://esterraapartments.com",
      "status": "error",
      "signal": "none",
      "details": "",
      "checked_at": "2026-03-19T19:54:59.584134+00:00",
      "error": "connection_error",
      "has_3br": false,
      "has_den": false,
      "in_budget": true
    },
    "Excalibur Apartment Homes": {
      "name": "Excalibur Apartment Homes",
      "city": "Bellevue",
      "url": "https://www.excaliburbellevue.com",
      "status": "error",
      "signal": "none",
      "details": "",
      "checked_at": "2026-03-19T19:55:01.125035+00:00",
      "error": "403 Client Error: Forbidden for url: https://www.excaliburbellevue.com/",
      "has_3br": false,
      "has_den": false,
      "in_budget": true
    },
    "Hanson": {
      "name": "Hanson",
      "city": "Bellevue",
      "url": "https://www.bellevuedowntown.com/go/the-carlyle-condominiums",
      "status": "unknown",
      "signal": "none",
      "details": "No clear availability signal | den/loft detected",
      "checked_at": "2026-03-19T19:55:02.891068+00:00",
      "error": null,
      "has_3br": false,
      "has_den": true,
      "in_budget": true
    },
    "Hyde Square": {
      "name": "Hyde Square",
      "city": "Bellevue",
      "url": "https://hydesquare.com/",
      "status": "unknown",
      "signal": "none",
      "details": "No clear availability signal | den/loft detected",
      "checked_at": "2026-03-19T19:55:04.638406+00:00",
      "error": null,
      "has_3br": false,
      "has_den": true,
      "in_budget": true
    },
    "Lake Hills Apartments": {
      "name": "Lake Hills Apartments",
      "city": "Bellevue",
      "url": "https://www.lakehillsapts.com",
      "status": "error",
      "signal": "none",
      "details": "",
      "checked_at": "2026-03-19T19:55:06.678073+00:00",
      "error": "connection_error",
      "has_3br": false,
      "has_den": false,
      "in_budget": true
    },
    "Lux": {
      "name": "Lux",
      "city": "Bellevue",
      "url": "https://www.rentatlux.com",
      "status": "error",
      "signal": "none",
      "details": "",
      "checked_at": "2026-03-19T19:55:08.264823+00:00",
      "error": "403 Client Error: Forbidden for url: https://www.rentatlux.com/",
      "has_3br": false,
      "has_den": false,
      "in_budget": true
    },
    "Madison Bellevue Apartments": {
      "name": "Madison Bellevue Apartments",
      "city": "Bellevue",
      "url": "https://www.madison-bellevue.com",
      "status": "error",
      "signal": "none",
      "details": "",
      "checked_at": "2026-03-19T19:55:10.089509+00:00",
      "error": "403 Client Error: Forbidden for url: https://www.madison-bellevue.com/",
      "has_3br": false,
      "has_den": false,
      "in_budget": true
    },
    "Milano": {
      "name": "Milano",
      "city": "Bellevue",
      "url": "https://www.milanoapts.com/",
      "status": "available",
      "signal": "strong",
      "details": "Keywords: vacancies [den/loft]",
      "checked_at": "2026-03-19T19:55:11.829144+00:00",
      "error": null,
      "has_3br": false,
      "has_den": true,
      "in_budget": true
    },
    "Mira Flats": {
      "name": "Mira Flats",
      "city": "Bellevue",
      "url": "https://www.miraflats.com",
      "status": "available",
      "signal": "strong",
      "details": "Keywords: move-in ready [3BR, den/loft]",
      "checked_at": "2026-03-19T19:55:13.532919+00:00",
      "error": null,
      "has_3br": true,
      "has_den": true,
      "in_budget": true
    },
    "Northpoint Apartments": {
      "name": "Northpoint Apartments",
      "city": "Bellevue",
      "url": "https://www.northpointbellevue.com",
      "status": "error",
      "signal": "none",
      "details": "",
      "checked_at": "2026-03-19T19:55:15.241197+00:00",
      "error": "connection_error",
      "has_3br": false,
      "has_den": false,
      "in_budget": true
    },
    "Nuovo": {
      "name": "Nuovo",
      "city": "Bellevue",
      "url": "https://www.nuovobellevue.com/",
      "status": "error",
      "signal": "none",
      "details": "",
      "checked_at": "2026-03-19T19:55:16.831655+00:00",
      "error": "403 Client Error: Forbidden for url: https://www.nuovobellevue.com/",
      "has_3br": false,
      "has_den": false,
      "in_budget": true
    },
    "Ondina": {
      "name": "Ondina",
      "city": "Bellevue",
      "url": "https://liveondina.com/floorplans/",
      "status": "available",
      "signal": "strong",
      "details": "Keywords: apply now [den/loft]",
      "checked_at": "2026-03-19T19:55:18.462587+00:00",
      "error": null,
      "has_3br": false,
      "has_den": true,
      "in_budget": true
    },
    "Park 88": {
      "name": "Park 88",
      "city": "Bellevue",
      "url": "https://www.park88.com",
      "status": "available",
      "signal": "strong",
      "details": "Keywords: apply now, check availability [den/loft]",
      "checked_at": "2026-03-19T19:55:20.416659+00:00",
      "error": null,
      "has_3br": false,
      "has_den": true,
      "in_budget": true,
      "min_rent_found": 1000
    },
    "Park Bellevue": {
      "name": "Park Bellevue",
      "city": "Bellevue",
      "url": "https://www.rentparkbellevue.com",
      "status": "available",
      "signal": "strong",
      "details": "Keywords: apply now, schedule a tour [3BR, den/loft]",
      "checked_at": "2026-03-19T19:55:22.393417+00:00",
      "error": null,
      "has_3br": true,
      "has_den": true,
      "in_budget": true,
      "min_rent_found": 1980
    },
    "Park Highlands": {
      "name": "Park Highlands",
      "city": "Bellevue",
      "url": "https://www.essexapartmenthomes.com/apartments/bellevue/park-highland",
      "status": "available",
      "signal": "strong",
      "details": "Keywords: apply now, schedule a tour [3BR, den/loft]",
      "checked_at": "2026-03-19T19:55:24.053203+00:00",
      "error": null,
      "has_3br": true,
      "has_den": true,
      "in_budget": true,
      "min_rent_found": 1837
    },
    "Polaris at Eastgate": {
      "name": "Polaris at Eastgate",
      "city": "Bellevue",
      "url": "https://www.liveatpolarisateastgate.com/",
      "status": "unknown",
      "signal": "none",
      "details": "No clear availability signal | 3BR detected, den/loft detected",
      "checked_at": "2026-03-19T19:55:27.225351+00:00",
      "error": null,
      "has_3br": true,
      "has_den": true,
      "in_budget": true
    },
    "Redmond Park": {
      "name": "Redmond Park",
      "city": "Bellevue",
      "url": "https://www.redmondparkapts.com/",
      "status": "available",
      "signal": "strong",
      "details": "Keywords: available now, schedule a tour [den/loft]",
      "checked_at": "2026-03-19T19:55:29.352447+00:00",
      "error": null,
      "has_3br": false,
      "has_den": true,
      "in_budget": true,
      "min_rent_found": 1000
    },
    "Sir Gallahad Apartment Homes": {
      "name": "Sir Gallahad Apartment Homes",
      "city": "Bellevue",
      "url": "https://www.sirgallahadbellevue.com",
      "status": "error",
      "signal": "none",
      "details": "",
      "checked_at": "2026-03-19T19:55:33.542965+00:00",
      "error": "403 Client Error: Forbidden for url: https://www.sirgallahadbellevue.com/",
      "has_3br": false,
      "has_den": false,
      "in_budget": true
    },
    "Soma Towers": {
      "name": "Soma Towers",
      "city": "Bellevue",
      "url": "https://somatowersapts.com/",
      "status": "error",
      "signal": "none",
      "details": "",
      "checked_at": "2026-03-19T19:55:35.314021+00:00",
      "error": "403 Client Error: Forbidden for url: https://www.somatowersapts.com",
      "has_3br": false,
      "has_den": false,
      "in_budget": true
    },
    "Stokely": {
      "name": "Stokely",
      "city": "Bellevue",
      "url": "https://www.livestokely.com/floorplans/",
      "status": "available",
      "signal": "strong",
      "details": "Keywords: apply now, available units [den/loft]",
      "checked_at": "2026-03-19T19:55:37.122247+00:00",
      "error": null,
      "has_3br": false,
      "has_den": true,
      "in_budget": true
    },
    "Summit Apartments": {
      "name": "Summit Apartments",
      "city": "Bellevue",
      "url": "https://www.livesummitredmond.com/",
      "status": "available",
      "signal": "strong",
      "details": "Keywords: available now, move-in ready [den/loft]",
      "checked_at": "2026-03-19T19:55:41.018596+00:00",
      "error": null,
      "has_3br": false,
      "has_den": true,
      "in_budget": true
    },
    "TEN20": {
      "name": "TEN20",
      "city": "Bellevue",
      "url": "https://www.udr.com/seattle-apartments/bellevue/ten20/",
      "status": "unknown",
      "signal": "none",
      "details": "No clear availability signal | den/loft detected",
      "checked_at": "2026-03-19T19:55:42.831059+00:00",
      "error": null,
      "has_3br": false,
      "has_den": true,
      "in_budget": true,
      "min_rent_found": 1897
    },
    "The Ashton Bellevue": {
      "name": "The Ashton Bellevue",
      "city": "Bellevue",
      "url": "https://www.udr.com/seattle-apartments/bellevue/ashton-bellevue/apartments-pricing/",
      "status": "available",
      "signal": "strong",
      "details": "Keywords: available floor, \\d+ available [den/loft]",
      "checked_at": "2026-03-19T19:55:45.115676+00:00",
      "error": null,
      "has_3br": false,
      "has_den": true,
      "in_budget": true,
      "min_rent_found": 1897
    },
    "The Charles": {
      "name": "The Charles",
      "city": "Bellevue",
      "url": "https://www.thecharlesbellevue.com",
      "status": "error",
      "signal": "none",
      "details": "",
      "checked_at": "2026-03-19T19:55:47.347885+00:00",
      "error": "connection_error",
      "has_3br": false,
      "has_den": false,
      "in_budget": true
    },
    "The Meyden": {
      "name": "The Meyden",
      "city": "Bellevue",
      "url": "https://www.themeydenbellevue.com/floor-plans",
      "status": "available",
      "signal": "strong",
      "details": "Keywords: apply now, schedule a tour [den/loft]",
      "checked_at": "2026-03-19T19:55:48.883933+00:00",
      "error": null,
      "has_3br": false,
      "has_den": true,
      "in_budget": true
    },
    "The Park in Bellevue": {
      "name": "The Park in Bellevue",
      "city": "Bellevue",
      "url": "https://www.rentparkbellevue.com/floor-plans",
      "status": "available",
      "signal": "strong",
      "details": "Keywords: apply now, schedule a tour [den/loft]",
      "checked_at": "2026-03-19T19:55:50.642064+00:00",
      "error": null,
      "has_3br": false,
      "has_den": true,
      "in_budget": true
    },
    "The Regent at Bellevue Way": {
      "name": "The Regent at Bellevue Way",
      "city": "Bellevue",
      "url": "https://www.theregentatbellevueway.com/floorplans",
      "status": "error",
      "signal": "none",
      "details": "",
      "checked_at": "2026-03-19T19:55:52.303235+00:00",
      "error": "403 Client Error: Forbidden for url: https://www.theregentatbellevueway.com/floorplans",
      "has_3br": false,
      "has_den": false,
      "in_budget": true
    },
    "Venn at Main": {
      "name": "Venn at Main",
      "city": "Bellevue",
      "url": "https://www.equityapartments.com/seattle/downtown-bellevue/venn-at-main-apartments",
      "status": "error",
      "signal": "none",
      "details": "",
      "checked_at": "2026-03-19T19:55:53.982198+00:00",
      "error": "403 Client Error: Forbidden for url: https://www.equityapartments.com/seattle/downtown-bellevue/venn",
      "has_3br": false,
      "has_den": false,
      "in_budget": true
    },
    "Vicino": {
      "name": "Vicino",
      "city": "Bellevue",
      "url": "https://www.hollandresidential.com/wa/bellevue/vicino",
      "status": "available",
      "signal": "strong",
      "details": "Keywords: now leasing [den/loft]",
      "checked_at": "2026-03-19T19:55:55.533617+00:00",
      "error": null,
      "has_3br": false,
      "has_den": true,
      "in_budget": true
    },
    "Vue 22": {
      "name": "Vue 22",
      "city": "Bellevue",
      "url": "https://www.vue22apts.com/",
      "status": "error",
      "signal": "none",
      "details": "",
      "checked_at": "2026-03-19T19:55:58.159916+00:00",
      "error": "403 Client Error: Forbidden for url: https://www.vue22apts.com/",
      "has_3br": false,
      "has_den": false,
      "in_budget": true
    },
    "Anthology": {
      "name": "Anthology",
      "city": "Issaquah",
      "url": "https://home.securityproperties.com/anthology/issaquah-wa-apartments/anthology-apartments/conventional/",
      "status": "error",
      "signal": "none",
      "details": "",
      "checked_at": "2026-03-19T19:55:59.835965+00:00",
      "error": "403 Client Error: Forbidden for url: https://home.securityproperties.com/anthology/issaquah-wa-apart",
      "has_3br": false,
      "has_den": false,
      "in_budget": true
    },
    "Boulder Creek": {
      "name": "Boulder Creek",
      "city": "Issaquah",
      "url": "https://www.bouldercreekapts.net/floorplans",
      "status": "error",
      "signal": "none",
      "details": "",
      "checked_at": "2026-03-19T19:56:01.515833+00:00",
      "error": "403 Client Error: Forbidden for url: https://www.bouldercreekapts.net/floorplans",
      "has_3br": false,
      "has_den": false,
      "in_budget": true
    },
    "Discovery Heights": {
      "name": "Discovery Heights",
      "city": "Issaquah",
      "url": "https://www.discoverywa.com/",
      "status": "error",
      "signal": "none",
      "details": "",
      "checked_at": "2026-03-19T19:56:03.207846+00:00",
      "error": "403 Client Error: Forbidden for url: https://www.discoverywa.com/",
      "has_3br": false,
      "has_den": false,
      "in_budget": true
    },
    "Highlands at Wynhaven": {
      "name": "Highlands at Wynhaven",
      "city": "Issaquah",
      "url": "https://www.essexapartmenthomes.com/apartments/issaquah/the-highlands-at-wynhaven",
      "status": "available",
      "signal": "strong",
      "details": "Keywords: apply now, schedule a tour [3BR, den/loft]",
      "checked_at": "2026-03-19T19:56:04.883580+00:00",
      "error": null,
      "has_3br": true,
      "has_den": true,
      "in_budget": true,
      "min_rent_found": 1839
    },
    "Summerwalk at Klahanie": {
      "name": "Summerwalk at Klahanie",
      "city": "Issaquah",
      "url": "https://www.hollandresidential.com/wa/issaquah/summerwalk-at-klahanie/floorplans",
      "status": "unknown",
      "signal": "none",
      "details": "No clear availability signal | den/loft detected",
      "checked_at": "2026-03-19T19:56:08.223547+00:00",
      "error": null,
      "has_3br": false,
      "has_den": true,
      "in_budget": true
    },
    "The Highlands at Wynhaven": {
      "name": "The Highlands at Wynhaven",
      "city": "Issaquah",
      "url": "https://www.essexapartmenthomes.com/apartments/issaquah/the-highlands-at-wynhaven",
      "status": "available",
      "signal": "strong",
      "details": "Keywords: apply now, schedule a tour [3BR, den/loft]",
      "checked_at": "2026-03-19T19:56:11.512483+00:00",
      "error": null,
      "has_3br": true,
      "has_den": true,
      "in_budget": true,
      "min_rent_found": 1839
    },
    "The Timbers": {
      "name": "The Timbers",
      "city": "Issaquah",
      "url": "https://www.simpsonpropertygroup.com/apartments/issaquah-washington/the-timbers-issaquah/apartment-floor-plans",
      "status": "error",
      "signal": "none",
      "details": "",
      "checked_at": "2026-03-19T19:56:15.061278+00:00",
      "error": "403 Client Error: Forbidden for url: https://www.simpsonpropertygroup.com/apartments/issaquah-washin",
      "has_3br": false,
      "has_den": false,
      "in_budget": true
    },
    "Vale": {
      "name": "Vale",
      "city": "Issaquah",
      "url": "https://liveatvale.com/",
      "status": "available",
      "signal": "strong",
      "details": "Keywords: apply now [den/loft]",
      "checked_at": "2026-03-19T19:56:18.312415+00:00",
      "error": null,
      "has_3br": false,
      "has_den": true,
      "in_budget": true
    },
    "Hiatt Springs": {
      "name": "Hiatt Springs",
      "city": "Kenmore",
      "url": "https://www.kcha.org/housing/city.aspx?city=kenmore",
      "status": "waitlist",
      "signal": "waitlist",
      "details": "Waitlist keywords: not currently accepting",
      "checked_at": "2026-03-19T19:56:19.974330+00:00",
      "error": null,
      "has_3br": false,
      "has_den": true,
      "in_budget": true
    },
    "Northlake Grove Cooperative": {
      "name": "Northlake Grove Cooperative",
      "city": "Kenmore",
      "url": "https://www.compasshousingalliance.org/affordable-housing/northlake-grove-cooperative/",
      "status": "unknown",
      "signal": "none",
      "details": "No clear availability signal | den/loft detected",
      "checked_at": "2026-03-19T19:56:22.778438+00:00",
      "error": null,
      "has_3br": false,
      "has_den": true,
      "in_budget": true
    },
    "Spencer 68": {
      "name": "Spencer 68",
      "city": "Kenmore",
      "url": "https://www.liveatspencer68.com/",
      "status": "error",
      "signal": "none",
      "details": "",
      "checked_at": "2026-03-19T19:56:24.695538+00:00",
      "error": "403 Client Error: Forbidden for url: https://www.liveatspencer68.com/",
      "has_3br": false,
      "has_den": false,
      "in_budget": true
    },
    "Ascent": {
      "name": "Ascent",
      "city": "Kirkland",
      "url": "https://www.essexapartmenthomes.com/apartments/kirkland/ascent",
      "status": "available",
      "signal": "strong",
      "details": "Keywords: apply now, schedule a tour [3BR, den/loft]",
      "checked_at": "2026-03-19T19:56:26.526778+00:00",
      "error": null,
      "has_3br": true,
      "has_den": true,
      "in_budget": true,
      "min_rent_found": 1967
    },
    "Aspen Townhomes": {
      "name": "Aspen Townhomes",
      "city": "Kirkland",
      "url": "https://www.archhousing.org/affordable-apartment-list",
      "status": "waitlist_or_limited",
      "signal": "mixed",
      "details": "Available: ['vacancies'], Waitlist: ['waitlist']",
      "checked_at": "2026-03-19T19:56:29.734833+00:00",
      "error": null,
      "has_3br": false,
      "has_den": false,
      "in_budget": true
    },
    "Boardwalk": {
      "name": "Boardwalk",
      "city": "Kirkland",
      "url": "https://kirklandboardwalk.com/",
      "status": "available",
      "signal": "strong",
      "details": "Keywords: apply now [den/loft]",
      "checked_at": "2026-03-19T19:56:31.661711+00:00",
      "error": null,
      "has_3br": false,
      "has_den": true,
      "in_budget": true
    },
    "Crestline Apartments": {
      "name": "Crestline Apartments",
      "city": "Kirkland",
      "url": "https://neiders.com/property/crestline-apartments-washington-kirkland-apartment/",
      "status": "unknown",
      "signal": "none",
      "details": "No clear availability signal | 3BR detected, den/loft detected",
      "checked_at": "2026-03-19T19:56:33.408163+00:00",
      "error": null,
      "has_3br": true,
      "has_den": true,
      "in_budget": true,
      "min_rent_found": 1100
    },
    "Grata at Totem Lake": {
      "name": "Grata at Totem Lake",
      "city": "Kirkland",
      "url": "https://www.liveatgrata.com/",
      "status": "unknown",
      "signal": "none",
      "details": "No clear availability signal | den/loft detected",
      "checked_at": "2026-03-19T19:56:35.353024+00:00",
      "error": null,
      "has_3br": false,
      "has_den": true,
      "in_budget": true
    },
    "Houghton Apartments": {
      "name": "Houghton Apartments",
      "city": "Kirkland",
      "url": "https://www.kcha.org/housing/property.aspx?PropertyID=167",
      "status": "waitlist_or_limited",
      "signal": "mixed",
      "details": "Available: ['vacancies'], Waitlist: ['not currently accepting']",
      "checked_at": "2026-03-19T19:56:37.436127+00:00",
      "error": null,
      "has_3br": true,
      "has_den": true,
      "in_budget": true
    },
    "Kirkland Crossing": {
      "name": "Kirkland Crossing",
      "city": "Kirkland",
      "url": "https://www.liveatkirklandcrossing.com/",
      "status": "error",
      "signal": "none",
      "details": "",
      "checked_at": "2026-03-19T19:56:40.394081+00:00",
      "error": "403 Client Error: Forbidden for url: https://www.liveatkirklandcrossing.com/",
      "has_3br": false,
      "has_den": false,
      "in_budget": true
    },
    "SK Apartments": {
      "name": "SK Apartments",
      "city": "Kirkland",
      "url": "https://www.skapartments.com/?p=1&nocache=1",
      "status": "error",
      "signal": "none",
      "details": "",
      "checked_at": "2026-03-19T19:56:42.200655+00:00",
      "error": "403 Client Error: Forbidden for url: https://www.skapartments.com/?p=1&nocache=1",
      "has_3br": false,
      "has_den": false,
      "in_budget": true
    },
    "The Pine": {
      "name": "The Pine",
      "city": "Kirkland",
      "url": "https://thepinekirkland.com/",
      "status": "available",
      "signal": "strong",
      "details": "Keywords: schedule a tour [3BR, den/loft]",
      "checked_at": "2026-03-19T19:56:44.010143+00:00",
      "error": null,
      "has_3br": true,
      "has_den": true,
      "in_budget": true
    },
    "Uplund": {
      "name": "Uplund",
      "city": "Kirkland",
      "url": "https://www.uplundkirkland.com/",
      "status": "available",
      "signal": "strong",
      "details": "Keywords: units available, schedule a tour [3BR, den/loft]",
      "checked_at": "2026-03-19T19:56:45.993547+00:00",
      "error": null,
      "has_3br": true,
      "has_den": true,
      "in_budget": true,
      "min_rent_found": 1962
    },
    "Uptown at Kirkland Urban": {
      "name": "Uptown at Kirkland Urban",
      "city": "Kirkland",
      "url": "https://washington.weidner.com/apartments/wa/kirkland/uptown-at-kirkland-urban",
      "status": "error",
      "signal": "none",
      "details": "",
      "checked_at": "2026-03-19T19:56:51.771392+00:00",
      "error": "403 Client Error: Forbidden for url: https://washington.weidner.com/apartments/wa/kirkland/uptown-at",
      "has_3br": false,
      "has_den": false,
      "in_budget": true
    },
    "Hadley": {
      "name": "Hadley",
      "city": "Mercer Island",
      "url": "https://hadleymercerisland.com/",
      "status": "available",
      "signal": "strong",
      "details": "Keywords: apply now, schedule a tour [den/loft]",
      "checked_at": "2026-03-19T19:56:53.458599+00:00",
      "error": null,
      "has_3br": false,
      "has_den": true,
      "in_budget": true
    },
    "Island Square": {
      "name": "Island Square",
      "city": "Mercer Island",
      "url": "https://www.udr.com/seattle-apartments/mercer-island/island-square/",
      "status": "available",
      "signal": "strong",
      "details": "Keywords: view available, available.*\\d+ bed [den/loft]",
      "checked_at": "2026-03-19T19:56:56.037805+00:00",
      "error": null,
      "has_3br": false,
      "has_den": true,
      "in_budget": true,
      "min_rent_found": 1897
    },
    "The Mercer Apartment Homes": {
      "name": "The Mercer Apartment Homes",
      "city": "Mercer Island",
      "url": "https://www.themercer.com",
      "status": "error",
      "signal": "none",
      "details": "",
      "checked_at": "2026-03-19T19:56:58.271552+00:00",
      "error": "403 Client Error: Forbidden for url: https://www.themercer.com/",
      "has_3br": false,
      "has_den": false,
      "in_budget": true
    },
    "Avalon Newcastle": {
      "name": "Avalon Newcastle",
      "city": "Newcastle",
      "url": "https://www.avaloncommunities.com/washington/newcastle-apartments/avalon-newcastle/",
      "status": "error",
      "signal": "none",
      "details": "",
      "checked_at": "2026-03-19T19:56:59.903752+00:00",
      "error": "404 Client Error: Not Found for url: https://www.avaloncommunities.com/washington/newcastle-apartmen",
      "has_3br": false,
      "has_den": false,
      "in_budget": true
    },
    "Avalon Newcastle Commons": {
      "name": "Avalon Newcastle Commons",
      "city": "Newcastle",
      "url": "https://www.avaloncommunities.com/washington/newcastle-apartments/avalon-newcastle-commons/",
      "status": "available",
      "signal": "strong",
      "details": "Keywords: \\d+ available, available.*\\d+ bed [den/loft]",
      "checked_at": "2026-03-19T19:57:01.909738+00:00",
      "error": null,
      "has_3br": false,
      "has_den": true,
      "in_budget": true
    },
    "The Notch": {
      "name": "The Notch",
      "city": "Newcastle",
      "url": "https://www.equityapartments.com/seattle/newcastle/notch-apartments",
      "status": "error",
      "signal": "none",
      "details": "",
      "checked_at": "2026-03-19T19:57:03.909712+00:00",
      "error": "403 Client Error: Forbidden for url: https://www.equityapartments.com/seattle/newcastle/notch-apartm",
      "has_3br": false,
      "has_den": false,
      "in_budget": true
    },
    "Tria": {
      "name": "Tria",
      "city": "Newcastle",
      "url": "https://home.securityproperties.com/tria/",
      "status": "error",
      "signal": "none",
      "details": "",
      "checked_at": "2026-03-19T19:57:05.467318+00:00",
      "error": "403 Client Error: Forbidden for url: https://home.securityproperties.com/tria/",
      "has_3br": false,
      "has_den": false,
      "in_budget": true
    },
    "AVA Esterra Park": {
      "name": "AVA Esterra Park",
      "city": "Redmond",
      "url": "https://www.avaloncommunities.com/washington/redmond-apartments/ava-esterra-park/",
      "status": "available",
      "signal": "strong",
      "details": "Keywords: \\d+ available [den/loft]",
      "checked_at": "2026-03-19T19:57:07.082352+00:00",
      "error": null,
      "has_3br": false,
      "has_den": true,
      "in_budget": true
    },
    "Allez": {
      "name": "Allez",
      "city": "Redmond",
      "url": "https://www.allezliving.com/",
      "status": "error",
      "signal": "none",
      "details": "",
      "checked_at": "2026-03-19T19:57:11.312273+00:00",
      "error": "403 Client Error: Forbidden for url: https://www.allezliving.com/",
      "has_3br": false,
      "has_den": false,
      "in_budget": true
    },
    "Aria Flats": {
      "name": "Aria Flats",
      "city": "Redmond",
      "url": "https://ariaredmond.com/",
      "status": "available",
      "signal": "strong",
      "details": "Keywords: apply now [den/loft]",
      "checked_at": "2026-03-19T19:57:12.933942+00:00",
      "error": null,
      "has_3br": false,
      "has_den": true,
      "in_budget": true,
      "min_rent_found": 1995
    },
    "Avalon Downtown Redmond": {
      "name": "Avalon Downtown Redmond",
      "city": "Redmond",
      "url": "https://www.avaloncommunities.com/washington/redmond-apartments/avalon-downtown-redmond/",
      "status": "error",
      "signal": "none",
      "details": "",
      "checked_at": "2026-03-19T19:57:14.629674+00:00",
      "error": "404 Client Error: Not Found for url: https://www.avaloncommunities.com/washington/redmond-apartments",
      "has_3br": false,
      "has_den": false,
      "in_budget": true
    },
    "Avalon ParcSquare": {
      "name": "Avalon ParcSquare",
      "city": "Redmond",
      "url": "https://www.avaloncommunities.com/washington/redmond-apartments/avalon-parcsquare/",
      "status": "available",
      "signal": "strong",
      "details": "Keywords: \\d+ available, available.*\\d+ bed [den/loft]",
      "checked_at": "2026-03-19T19:57:16.375381+00:00",
      "error": null,
      "has_3br": false,
      "has_den": true,
      "in_budget": true
    },
    "Avalon at Bear Creek": {
      "name": "Avalon at Bear Creek",
      "city": "Redmond",
      "url": "https://www.avaloncommunities.com/washington/redmond-apartments/avalon-at-bear-creek/",
      "status": "available",
      "signal": "strong",
      "details": "Keywords: \\d+ available, available.*\\d+ bed [3BR, den/loft]",
      "checked_at": "2026-03-19T19:57:19.260083+00:00",
      "error": null,
      "has_3br": true,
      "has_den": true,
      "in_budget": true
    },
    "Avignon Townhomes": {
      "name": "Avignon Townhomes",
      "city": "Redmond",
      "url": "https://www.avignontownhomes.com/Floor-plans.aspx",
      "status": "available",
      "signal": "strong",
      "details": "Keywords: schedule a tour [den/loft]",
      "checked_at": "2026-03-19T19:57:22.589976+00:00",
      "error": null,
      "has_3br": false,
      "has_den": true,
      "in_budget": true
    },
    "Blackbird": {
      "name": "Blackbird",
      "city": "Redmond",
      "url": "https://www.blackbirdredmond.com/",
      "status": "available",
      "signal": "strong",
      "details": "Keywords: apply now, schedule a tour [den/loft]",
      "checked_at": "2026-03-19T19:57:24.428367+00:00",
      "error": null,
      "has_3br": false,
      "has_den": true,
      "in_budget": true
    },
    "BonTerra": {
      "name": "BonTerra",
      "city": "Redmond",
      "url": "https://bonterraapartments.propertyware.com/about_us.html",
      "status": "unknown",
      "signal": "none",
      "details": "No clear availability signal",
      "checked_at": "2026-03-19T19:57:26.263714+00:00",
      "error": null,
      "has_3br": false,
      "has_den": false,
      "in_budget": true
    },
    "Camden Redmond": {
      "name": "Camden Redmond",
      "city": "Redmond",
      "url": "https://www.camdenliving.com/apartments/redmond-wa/camden-redmond",
      "status": "unknown",
      "signal": "none",
      "details": "No clear availability signal | 3BR detected, den/loft detected",
      "checked_at": "2026-03-19T19:57:27.999894+00:00",
      "error": null,
      "has_3br": true,
      "has_den": true,
      "in_budget": true,
      "min_rent_found": 1169
    },
    "Capella at Esterra Park": {
      "name": "Capella at Esterra Park",
      "city": "Redmond",
      "url": "https://www.capellaesterra.com/",
      "status": "error",
      "signal": "none",
      "details": "",
      "checked_at": "2026-03-19T19:57:30.139322+00:00",
      "error": "connection_error",
      "has_3br": false,
      "has_den": false,
      "in_budget": true
    },
    "Cleveland Square": {
      "name": "Cleveland Square",
      "city": "Redmond",
      "url": "https://www.clevelandsquareredmond.com",
      "status": "error",
      "signal": "none",
      "details": "",
      "checked_at": "2026-03-19T19:57:31.673118+00:00",
      "error": "connection_error",
      "has_3br": false,
      "has_den": false,
      "in_budget": true
    },
    "Core 83": {
      "name": "Core 83",
      "city": "Redmond",
      "url": "https://www.thecore83.com/",
      "status": "error",
      "signal": "none",
      "details": "",
      "checked_at": "2026-03-19T19:57:33.202164+00:00",
      "error": "403 Client Error: Forbidden for url: https://www.thecore83.com/",
      "has_3br": false,
      "has_den": false,
      "in_budget": true
    },
    "Cru": {
      "name": "Cru",
      "city": "Redmond",
      "url": "https://www.cruatwillows.com/",
      "status": "error",
      "signal": "none",
      "details": "",
      "checked_at": "2026-03-19T19:57:34.854715+00:00",
      "error": "403 Client Error: Forbidden for url: https://www.cruatwillows.com/",
      "has_3br": false,
      "has_den": false,
      "in_budget": true
    },
    "Delano": {
      "name": "Delano",
      "city": "Redmond",
      "url": "https://www.delanoredmond.com/",
      "status": "error",
      "signal": "none",
      "details": "",
      "checked_at": "2026-03-19T19:57:36.458265+00:00",
      "error": "403 Client Error: Forbidden for url: https://www.delanoredmond.com/",
      "has_3br": false,
      "has_den": false,
      "in_budget": true
    },
    "Edge": {
      "name": "Edge",
      "city": "Redmond",
      "url": "https://www.edge.apartments/",
      "status": "error",
      "signal": "none",
      "details": "",
      "checked_at": "2026-03-19T19:57:38.092525+00:00",
      "error": "403 Client Error: Forbidden for url: https://www.edge.apartments/",
      "has_3br": false,
      "has_den": false,
      "in_budget": true
    },
    "Elan": {
      "name": "Elan",
      "city": "Redmond",
      "url": "https://www.elanredmond.com/",
      "status": "available",
      "signal": "strong",
      "details": "Keywords: apply now, schedule a tour [den/loft]",
      "checked_at": "2026-03-19T19:57:40.197133+00:00",
      "error": null,
      "has_3br": false,
      "has_den": true,
      "in_budget": true
    },
    "Elan Redmond": {
      "name": "Elan Redmond",
      "city": "Redmond",
      "url": "https://elanredmond.com",
      "status": "available",
      "signal": "strong",
      "details": "Keywords: apply now, schedule a tour [den/loft]",
      "checked_at": "2026-03-19T19:57:42.560305+00:00",
      "error": null,
      "has_3br": false,
      "has_den": true,
      "in_budget": true
    },
    "Everlight": {
      "name": "Everlight",
      "city": "Redmond",
      "url": "https://everlightapartments.com/floorplans/",
      "status": "unknown",
      "signal": "none",
      "details": "No clear availability signal | den/loft detected",
      "checked_at": "2026-03-19T19:57:44.526463+00:00",
      "error": null,
      "has_3br": false,
      "has_den": true,
      "in_budget": true
    },
    "Heron Flats & Lofts": {
      "name": "Heron Flats & Lofts",
      "city": "Redmond",
      "url": "https://www.liveatheron.com/",
      "status": "error",
      "signal": "none",
      "details": "",
      "checked_at": "2026-03-19T19:57:46.690265+00:00",
      "error": "403 Client Error: Forbidden for url: https://www.liveatheron.com/",
      "has_3br": false,
      "has_den": false,
      "in_budget": true
    },
    "Hue Apartments": {
      "name": "Hue Apartments",
      "city": "Redmond",
      "url": "https://www.liveathue.com",
      "status": "error",
      "signal": "none",
      "details": "",
      "checked_at": "2026-03-19T19:57:48.411544+00:00",
      "error": "403 Client Error: Forbidden for url: https://www.liveathue.com/",
      "has_3br": false,
      "has_den": false,
      "in_budget": true
    },
    "Milehouse": {
      "name": "Milehouse",
      "city": "Redmond",
      "url": "https://www.udr.com/seattle-apartments/redmond/milehouse/",
      "status": "available",
      "signal": "strong",
      "details": "Keywords: view available, available.*\\d+ bed [den/loft]",
      "checked_at": "2026-03-19T19:57:50.083868+00:00",
      "error": null,
      "has_3br": false,
      "has_den": true,
      "in_budget": true,
      "min_rent_found": 1809
    },
    "Modera Overlake": {
      "name": "Modera Overlake",
      "city": "Redmond",
      "url": "https://www.moderaoverlake.com/redmond/modera-overlake/conventional/",
      "status": "error",
      "signal": "none",
      "details": "",
      "checked_at": "2026-03-19T19:57:52.373388+00:00",
      "error": "403 Client Error: Forbidden for url: https://www.moderaoverlake.com/redmond/modera-overlake/conventi",
      "has_3br": false,
      "has_den": false,
      "in_budget": true
    },
    "Modera Redmond": {
      "name": "Modera Redmond",
      "city": "Redmond",
      "url": "https://www.moderaredmond.com/",
      "status": "error",
      "signal": "none",
      "details": "",
      "checked_at": "2026-03-19T19:57:54.102840+00:00",
      "error": "403 Client Error: Forbidden for url: https://www.northshorelodgeidaho.com/restaurant",
      "has_3br": false,
      "has_den": false,
      "in_budget": true
    },
    "Modera River Trail": {
      "name": "Modera River Trail",
      "city": "Redmond",
      "url": "https://www.moderarivertrail.com/redmond/modera-river-trail/conventional/",
      "status": "error",
      "signal": "none",
      "details": "",
      "checked_at": "2026-03-19T19:57:56.270349+00:00",
      "error": "403 Client Error: Forbidden for url: https://www.moderarivertrail.com/redmond/modera-river-trail/con",
      "has_3br": false,
      "has_den": false,
      "in_budget": true
    },
    "Old Town Lofts": {
      "name": "Old Town Lofts",
      "city": "Redmond",
      "url": "https://www.equityapartments.com/seattle/downtown-redmond/old-town-lofts-apartments?mkwid=sIBmEH6BS_dc&pcrid=&pkw=Old%20Town%20Lofts%20Apartments&pmt=e&utm_source=bing&utm_medium=cpc&utm_term=&utm_campaign=&utm_group=Old+Town+Lofts+Apartments&gclsrc=aw.ds",
      "status": "error",
      "signal": "none",
      "details": "",
      "checked_at": "2026-03-19T19:57:57.934065+00:00",
      "error": "403 Client Error: Forbidden for url: https://www.equityapartments.com/seattle/downtown-redmond/old-t",
      "has_3br": false,
      "has_den": false,
      "in_budget": true
    },
    "Overlake Village at Overlake Station": {
      "name": "Overlake Village at Overlake Station",
      "city": "Redmond",
      "url": "https://www.overlakestation.com/floorplans/",
      "status": "unknown",
      "signal": "none",
      "details": "No clear availability signal | den/loft detected",
      "checked_at": "2026-03-19T19:57:59.484680+00:00",
      "error": null,
      "has_3br": false,
      "has_den": true,
      "in_budget": true
    },
    "Parc Square": {
      "name": "Parc Square",
      "city": "Redmond",
      "url": "https://www.avaloncommunities.com/washington/redmond-apartments/avalon-parcsquare/",
      "status": "available",
      "signal": "strong",
      "details": "Keywords: \\d+ available, available.*\\d+ bed [den/loft]",
      "checked_at": "2026-03-19T19:58:01.697855+00:00",
      "error": null,
      "has_3br": false,
      "has_den": true,
      "in_budget": true
    },
    "Porch and Park": {
      "name": "Porch and Park",
      "city": "Redmond",
      "url": "https://porchandparkredmond.com/",
      "status": "available",
      "signal": "strong",
      "details": "Keywords: apply now [den/loft]",
      "checked_at": "2026-03-19T19:58:03.499179+00:00",
      "error": null,
      "has_3br": false,
      "has_den": true,
      "in_budget": true
    },
    "Ravello": {
      "name": "Ravello",
      "city": "Redmond",
      "url": "https://www.liveravello.com/",
      "status": "error",
      "signal": "none",
      "details": "",
      "checked_at": "2026-03-19T19:58:05.478892+00:00",
      "error": "403 Client Error: Forbidden for url: https://www.liveravello.com/",
      "has_3br": false,
      "has_den": false,
      "in_budget": true
    },
    "Red 160": {
      "name": "Red 160",
      "city": "Redmond",
      "url": "https://www.equityapartments.com/seattle/downtown-redmond/red160-apartments",
      "status": "error",
      "signal": "none",
      "details": "",
      "checked_at": "2026-03-19T19:58:07.166442+00:00",
      "error": "403 Client Error: Forbidden for url: https://www.equityapartments.com/seattle/downtown-redmond/red16",
      "has_3br": false,
      "has_den": false,
      "in_budget": true
    },
    "Redmond Place": {
      "name": "Redmond Place",
      "city": "Redmond",
      "url": "https://www.redmondplaceapts.com",
      "status": "available",
      "signal": "strong",
      "details": "Keywords: apply now, vacant [3BR, den/loft]",
      "checked_at": "2026-03-19T19:58:08.725102+00:00",
      "error": null,
      "has_3br": true,
      "has_den": true,
      "in_budget": true
    },
    "Redmond Ridge Apartments": {
      "name": "Redmond Ridge Apartments",
      "city": "Redmond",
      "url": "https://redmondridgeapts.com",
      "status": "error",
      "signal": "none",
      "details": "",
      "checked_at": "2026-03-19T19:58:10.564372+00:00",
      "error": "connection_error",
      "has_3br": false,
      "has_den": false,
      "in_budget": true
    },
    "Riverpark": {
      "name": "Riverpark",
      "city": "Redmond",
      "url": "https://www.equityapartments.com/seattle/downtown-redmond/riverpark-apartments",
      "status": "error",
      "signal": "none",
      "details": "",
      "checked_at": "2026-03-19T19:58:12.151557+00:00",
      "error": "403 Client Error: Forbidden for url: https://www.equityapartments.com/seattle/downtown-redmond/river",
      "has_3br": false,
      "has_den": false,
      "in_budget": true
    },
    "Shadowbrook Apartments": {
      "name": "Shadowbrook Apartments",
      "city": "Redmond",
      "url": "https://www.essexapartmenthomes.com/apartments/redmond/shadowbrook",
      "status": "available",
      "signal": "strong",
      "details": "Keywords: apply now, schedule a tour [3BR, den/loft]",
      "checked_at": "2026-03-19T19:58:13.704170+00:00",
      "error": null,
      "has_3br": true,
      "has_den": true,
      "in_budget": true,
      "min_rent_found": 1200
    },
    "Skyline Redmond": {
      "name": "Skyline Redmond",
      "city": "Redmond",
      "url": "https://www.skylineredmond.com",
      "status": "available",
      "signal": "strong",
      "details": "Keywords: apply now, available.*\\d+ bed [den/loft]",
      "checked_at": "2026-03-19T19:58:16.760130+00:00",
      "error": null,
      "has_3br": false,
      "has_den": true,
      "in_budget": true
    },
    "Spectra": {
      "name": "Spectra",
      "city": "Redmond",
      "url": "https://spectraapts.com/",
      "status": "available",
      "signal": "strong",
      "details": "Keywords: schedule a tour, check availability [den/loft]",
      "checked_at": "2026-03-19T19:58:18.462937+00:00",
      "error": null,
      "has_3br": false,
      "has_den": true,
      "in_budget": true
    },
    "Station House Lofts": {
      "name": "Station House Lofts",
      "city": "Redmond",
      "url": "https://www.stationhouseredmond.com/",
      "status": "available",
      "signal": "strong",
      "details": "Keywords: apply now, schedule a tour [den/loft]",
      "checked_at": "2026-03-19T19:58:20.557567+00:00",
      "error": null,
      "has_3br": false,
      "has_den": true,
      "in_budget": true
    },
    "Station House Redmond": {
      "name": "Station House Redmond",
      "city": "Redmond",
      "url": "https://liveatstationhouse.com",
      "status": "error",
      "signal": "none",
      "details": "",
      "checked_at": "2026-03-19T19:58:22.324232+00:00",
      "error": "connection_error",
      "has_3br": false,
      "has_den": false,
      "in_budget": true
    },
    "Talisman": {
      "name": "Talisman",
      "city": "Redmond",
      "url": "https://livetalisman.com/",
      "status": "available",
      "signal": "strong",
      "details": "Keywords: apply now [den/loft]",
      "checked_at": "2026-03-19T19:58:23.843033+00:00",
      "error": null,
      "has_3br": false,
      "has_den": true,
      "in_budget": true
    },
    "The Bond": {
      "name": "The Bond",
      "city": "Redmond",
      "url": "https://www.thebondredmond.com/",
      "status": "error",
      "signal": "none",
      "details": "",
      "checked_at": "2026-03-19T19:58:25.881064+00:00",
      "error": "403 Client Error: Forbidden for url: https://www.thebondredmond.com/",
      "has_3br": false,
      "has_den": false,
      "in_budget": true
    },
    "The Carter": {
      "name": "The Carter",
      "city": "Redmond",
      "url": "https://www.liveatthecarter.com/",
      "status": "error",
      "signal": "none",
      "details": "",
      "checked_at": "2026-03-19T19:58:27.511448+00:00",
      "error": "403 Client Error: Forbidden for url: https://www.liveatthecarter.com/",
      "has_3br": false,
      "has_den": false,
      "in_budget": true
    },
    "The Colony at Bear Creek": {
      "name": "The Colony at Bear Creek",
      "city": "Redmond",
      "url": "https://www.thecolonyatbearcreek.com/redmond-redmond/the-colony-at-bear-creek-the-colony-at-bear-creek/conventional/",
      "status": "error",
      "signal": "none",
      "details": "",
      "checked_at": "2026-03-19T19:58:29.241402+00:00",
      "error": "403 Client Error: Forbidden for url: https://www.thecolonyatbearcreek.com/redmond-redmond/the-colony",
      "has_3br": false,
      "has_den": false,
      "in_budget": true
    },
    "The Docks at Redmond Lakeview": {
      "name": "The Docks at Redmond Lakeview",
      "city": "Redmond",
      "url": "https://www.docksatredmond.com/apartments/wa/redmond/floor-plans",
      "status": "available",
      "signal": "strong",
      "details": "Keywords: apply now, schedule a tour [den/loft]",
      "checked_at": "2026-03-19T19:58:30.925022+00:00",
      "error": null,
      "has_3br": false,
      "has_den": true,
      "in_budget": true
    },
    "The Lodge": {
      "name": "The Lodge",
      "city": "Redmond",
      "url": "https://www.simpsonpropertygroup.com/apartments/redmond-washington/the-lodge-at-redmond-ridge",
      "status": "error",
      "signal": "none",
      "details": "",
      "checked_at": "2026-03-19T19:58:32.658557+00:00",
      "error": "403 Client Error: Forbidden for url: https://www.simpsonpropertygroup.com/apartments/redmond-washing",
      "has_3br": false,
      "has_den": false,
      "in_budget": true
    },
    "The Luke": {
      "name": "The Luke",
      "city": "Redmond",
      "url": "https://www.theluke.com/",
      "status": "available",
      "signal": "strong",
      "details": "Keywords: apply now, schedule a tour [den/loft]",
      "checked_at": "2026-03-19T19:58:34.214320+00:00",
      "error": null,
      "has_3br": false,
      "has_den": true,
      "in_budget": true
    },
    "The Spoke": {
      "name": "The Spoke",
      "city": "Redmond",
      "url": "https://thespokeredmond.com/",
      "status": "available",
      "signal": "strong",
      "details": "Keywords: apply now [den/loft]",
      "checked_at": "2026-03-19T19:58:35.856248+00:00",
      "error": null,
      "has_3br": false,
      "has_den": true,
      "in_budget": true
    },
    "The Triangle": {
      "name": "The Triangle",
      "city": "Redmond",
      "url": "https://www.triangleredmond.com/",
      "status": "available",
      "signal": "strong",
      "details": "Keywords: apply now [den/loft]",
      "checked_at": "2026-03-19T19:58:37.491805+00:00",
      "error": null,
      "has_3br": false,
      "has_den": true,
      "in_budget": true
    },
    "Townside Flats": {
      "name": "Townside Flats",
      "city": "Redmond",
      "url": "https://townsideflats.com",
      "status": "error",
      "signal": "none",
      "details": "",
      "checked_at": "2026-03-19T19:58:39.733584+00:00",
      "error": "403 Client Error: Forbidden for url: https://www.townsideflats.com",
      "has_3br": false,
      "has_den": false,
      "in_budget": true
    },
    "Triangle Redmond": {
      "name": "Triangle Redmond",
      "city": "Redmond",
      "url": "https://triangleredmond.com/floorplans/",
      "status": "available",
      "signal": "strong",
      "details": "Keywords: apply now [den/loft]",
      "checked_at": "2026-03-19T19:58:41.557331+00:00",
      "error": null,
      "has_3br": false,
      "has_den": true,
      "in_budget": true
    },
    "Veloce": {
      "name": "Veloce",
      "city": "Redmond",
      "url": "https://www.equityapartments.com/seattle/downtown-redmond/veloce-apartments?mkwid=seWqdJ0YM_dc&pcrid=&pkw=veloce%20apartments%20redmond&pmt=e&utm_source=bing&utm_medium=cpc&utm_term=&utm_campaign=&utm_group=Veloce+Apartments&gclsrc=aw.ds&&utm_source=bing&",
      "status": "error",
      "signal": "none",
      "details": "",
      "checked_at": "2026-03-19T19:58:43.720513+00:00",
      "error": "403 Client Error: Forbidden for url: https://www.equityapartments.com/seattle/downtown-redmond/veloc",
      "has_3br": false,
      "has_den": false,
      "in_budget": true
    },
    "eaves Redmond Campus": {
      "name": "eaves Redmond Campus",
      "city": "Redmond",
      "url": "https://www.avaloncommunities.com/washington/redmond-apartments/eaves-redmond-campus/",
      "status": "available",
      "signal": "strong",
      "details": "Keywords: \\d+ available, available.*\\d+ bed [den/loft]",
      "checked_at": "2026-03-19T19:58:45.273866+00:00",
      "error": null,
      "has_3br": false,
      "has_den": true,
      "in_budget": true
    },
    "SAMM": {
      "name": "SAMM",
      "city": "Sammamish",
      "url": "https://liveatsamm.com/",
      "status": "available",
      "signal": "strong",
      "details": "Keywords: apply now [den/loft]",
      "checked_at": "2026-03-19T19:58:48.252610+00:00",
      "error": null,
      "has_3br": false,
      "has_den": true,
      "in_budget": true
    },
    "Sky": {
      "name": "Sky",
      "city": "Sammamish",
      "url": "https://www.liveskysammamish.com/",
      "status": "error",
      "signal": "none",
      "details": "",
      "checked_at": "2026-03-19T19:58:49.901241+00:00",
      "error": "403 Client Error: Forbidden for url: https://www.liveskysammamish.com/",
      "has_3br": false,
      "has_den": false,
      "in_budget": true
    },
    "Eastrail Flats": {
      "name": "Eastrail Flats",
      "city": "Woodinville",
      "url": "https://www.eastrailflatswoodinville.com/",
      "status": "available",
      "signal": "strong",
      "details": "Keywords: move in today, apply now [den/loft]",
      "checked_at": "2026-03-19T19:58:51.706276+00:00",
      "error": null,
      "has_3br": false,
      "has_den": true,
      "in_budget": true
    }
  }
}